denokv/__init__.py
denokv/_datapath_pb2.py
denokv/_datapath_pb2.pyi
denokv/_kv_types.py
denokv/_kv_values.py
denokv/_kv_writes.py
denokv/_pycompat/__init__.py
denokv/_pycompat/dataclasses.py
denokv/_pycompat/enum.py
denokv/_pycompat/exceptions.py
denokv/_pycompat/protobuf.py
denokv/_pycompat/types.py
denokv/_pycompat/typing.py
denokv/_rfc3339.py
denokv/_utils.py
denokv/asyncio.py
denokv/auth.py
denokv/backoff.py
denokv/datapath.py
denokv/errors.py
denokv/info.py
denokv/kv.py
denokv/kv_keys.py
denokv/py.typed
denokv/result.py
denokv-0.1.0a0.dev180.dist-info/LICENSE.md
denokv-0.1.0a0.dev180.dist-info/METADATA
denokv-0.1.0a0.dev180.dist-info/WHEEL
denokv-0.1.0a0.dev180.dist-info/RECORD
