Metadata-Version: 2.3
Name: denokv
Version: 0.1.0a0.dev180
Summary: Connect to Deno KV databases from Python.
License: MIT
Author: Hal Blackburn
Author-email: hwtb2@cam.ac.uk
Requires-Python: >=3.9,<4.0
Classifier: Development Status :: 2 - Pre-Alpha
Classifier: Framework :: AsyncIO
Classifier: License :: OSI Approved :: MIT License
Classifier: Programming Language :: Python :: 3
Classifier: Programming Language :: Python :: 3.9
Classifier: Programming Language :: Python :: 3.10
Classifier: Programming Language :: Python :: 3.11
Classifier: Programming Language :: Python :: 3.12
Classifier: Programming Language :: Python :: 3.13
Classifier: Topic :: Database :: Front-Ends
Classifier: Topic :: Software Development :: Libraries :: Python Modules
Requires-Dist: aiohttp (>=3,<4)
Requires-Dist: foundationdb (>=6.2.4,<8)
Requires-Dist: protobuf (>=4.22.0,<6)
Requires-Dist: v8serialize (>=0.2.0-alpha.0,<0.3.0)
Requires-Dist: yarl (>=1,<2)
Project-URL: Documentation, https://github.com/h4l/denokv-python
Project-URL: Homepage, https://github.com/h4l/denokv-python
Project-URL: Repository, https://github.com/h4l/denokv-python
